colorsdude_g1gabyteDEV/__init__.py
colorsdude_g1gabyteDEV/yes.py
colorsdude_g1gabyteDEV-0.6.9.dist-info/LICENSE
colorsdude_g1gabyteDEV-0.6.9.dist-info/METADATA
colorsdude_g1gabyteDEV-0.6.9.dist-info/WHEEL
colorsdude_g1gabyteDEV-0.6.9.dist-info/top_level.txt
colorsdude_g1gabyteDEV-0.6.9.dist-info/RECORD
