Metadata-Version: 2.1
Name: colorsdude_g1gabyteDEV
Version: 0.6.9
Summary: A small package used for ez refrence to colors.
Author-email: James <me@g1gabyte.dev>
Classifier: Programming Language :: Python :: 3
Classifier: Operating System :: OS Independent
Requires-Python: >=3.0
License-File: LICENSE
